ecsjobs/__init__.py
ecsjobs/config.py
ecsjobs/reporter.py
ecsjobs/runner.py
ecsjobs/schema.py
ecsjobs/version.py
ecsjobs/jobs/__init__.py
ecsjobs/jobs/base.py
ecsjobs/jobs/docker_exec.py
ecsjobs/jobs/docker_exec_mixin.py
ecsjobs/jobs/ecs_docker_exec.py
ecsjobs/jobs/ecs_task.py
ecsjobs/jobs/local_command.py
ecsjobs/tests/__init__.py
ecsjobs/tests/test_config.py
ecsjobs/tests/test_reporter.py
ecsjobs/tests/test_runner.py
ecsjobs/tests/test_schema.py
ecsjobs/tests/test_version.py
ecsjobs/tests/jobs/__init__.py
ecsjobs/tests/jobs/test_base.py
ecsjobs/tests/jobs/test_docker_exec.py
ecsjobs/tests/jobs/test_docker_exec_mixin.py
ecsjobs/tests/jobs/test_ecs_docker_exec.py
ecsjobs/tests/jobs/test_ecs_task.py
ecsjobs/tests/jobs/test_init.py
ecsjobs/tests/jobs/test_local_command.py
ecsjobs-1.0.0.dist-info/LICENSE
ecsjobs-1.0.0.dist-info/METADATA
ecsjobs-1.0.0.dist-info/WHEEL
ecsjobs-1.0.0.dist-info/entry_points.txt
ecsjobs-1.0.0.dist-info/top_level.txt
ecsjobs-1.0.0.dist-info/RECORD
