Metadata-Version: 2.1
Name: ecsjobs
Version: 1.0.0
Summary: A scheduled job wrapper for ECS, focused on email reporting and adding docker exec and local command abilities.
Home-page: https://github.com/jantman/ecsjobs
Author: Jason Antman
Author-email: jason@jasonantman.com
License: UNKNOWN
Keywords: aws ecs cron email docker
Platform: UNKNOWN
Classifier: Development Status :: 6 - Mature
Classifier: Programming Language :: Python
Classifier: Programming Language :: Python :: 3
Classifier: License :: OSI Approved :: GNU Affero General Public License v3 or later (AGPLv3+)
License-File: LICENSE
Requires-Dist: boto3 (<2.0.0,>=1.0.0)
Requires-Dist: cronex (==0.1.0)
Requires-Dist: docker (<3.0.0,>=2.0.0)
Requires-Dist: jsonschema (<3.0.0,>=2.0.0)
Requires-Dist: PyYAML (>=3.0)
Requires-Dist: requests (<3.0.0,>=2.0.0)
